{"response":"success","id":"113","name":"Blaquesmith","powerstats":{"intelligence":"null","strength":"null","speed":"null","durability":"null","power":"null","combat":"null"},"biography":{"full-name":"-","alter-egos":"Vertigo II","aliases":["-"],"place-of-birth":"-","first-appearance":"-","publisher":"Vertigo II","alignment":"good"},"appearance":{"gender":"-","race":"null","height":["-","0 cm"],"weight":["- lb","0 kg"],"eye-color":"Black","hair-color":"No Hair"},"work":{"occupation":"Inventor","base":"Baltimore, Maryland"},"connections":{"group-affiliation":"Clan Askani/Clan Chosen","relatives":"-"},"image":{"url":"https://www.superherodb.com/pictures2/portraits/10/100/34.jpg"}}