{"response":"success","id":"304","name":"Guardian","powerstats":{"intelligence":"null","strength":"45","speed":"null","durability":"null","power":"null","combat":"null"},"biography":{"full-name":"James Hudson","alter-egos":"No alter egos found.","aliases":["Weapon Alpha","Antiguard","Vindicator","Mac","Jimmy"],"place-of-birth":"London, Ontario, Canada","first-appearance":"X-Men Vol.1  #109 (as Weapon Alpha)","publisher":"Marvel Comics","alignment":"good"},"appearance":{"gender":"Male","race":"Human","height":["-","0 cm"],"weight":["- lb","0 kg"],"eye-color":"Brown","hair-color":"Black"},"work":{"occupation":"Engineer, government agent, adventurer","base":"Ottawa, Canada"},"connections":{"group-affiliation":"Alpha Flight","relatives":"Vindicator II (Heather Hudson), wife"},"image":{"url":"https://www.superherodb.com/pictures2/portraits/10/100/76.jpg"}}