{"response":"success","id":"371","name":"Jolt","powerstats":{"intelligence":"63","strength":"12","speed":"27","durability":"32","power":"31","combat":"42"},"biography":{"full-name":"Helen Takahama","alter-egos":"No alter egos found.","aliases":["Holly Tsuruta","Hallie Shimosato"],"place-of-birth":"Ojai, California","first-appearance":"Thunderbolts #1 (1997)","publisher":"Marvel Comics","alignment":"good"},"appearance":{"gender":"Female","race":"null","height":["5'5","165 cm"],"weight":["109 lb","49 kg"],"eye-color":"Blue","hair-color":"Black"},"work":{"occupation":"Adventurer","base":"-"},"connections":{"group-affiliation":"Young Allies; formerly Redeemers, Thunderbolts","relatives":"Robert (father, deceased), Jane (mother, deceased)"},"image":{"url":"https://www.superherodb.com/pictures2/portraits/10/100/1323.jpg"}}