{"response":"success","id":"519","name":"Plastic Lad","powerstats":{"intelligence":"null","strength":"null","speed":"null","durability":"null","power":"null","combat":"null"},"biography":{"full-name":"Luke O'Brian","alter-egos":"No alter egos found.","aliases":["Offspring"],"place-of-birth":"-","first-appearance":"-","publisher":"DC Comics","alignment":"good"},"appearance":{"gender":"Male","race":"null","height":["-","0 cm"],"weight":["- lb","0 kg"],"eye-color":"-","hair-color":"-"},"work":{"occupation":"-","base":"-"},"connections":{"group-affiliation":"-","relatives":"-"},"image":{"url":"https://www.superherodb.com/pictures2/portraits/10/100/1299.jpg"}}