{"response":["success"],"id":["284"],"name":["Giganta"],"powerstats":{"intelligence":["81"],"strength":["89"],"speed":["23"],"durability":["85"],"power":["32"],"combat":["42"]},"biography":{"full-name":["Doris Zuel"],"alter-egos":["No alter egos found."],"aliases":["-"],"place-of-birth":["-"],"first-appearance":["Wonder Woman (Volume 1) #9 (1944)"],"publisher":["DC Comics"],"alignment":["bad"]},"appearance":{"gender":["Female"],"race":["null"],"height":["205","62.5 meters"],"weight":["1400 lb","630 kg"],"eye-color":["Green"],"hair-color":["Red"]},"work":{"occupation":["Criminal, former Scientist, Professor at Ivy University"],"base":["Ivy Town"]},"connections":{"group-affiliation":["Injustice League"],"relatives":["-"]},"image":{"url":["https://www.superherodb.com/pictures2/portraits/10/100/1376.jpg"]}}
