{"response":["success"],"id":["409"],"name":["Living Brain"],"powerstats":{"intelligence":["75"],"strength":["53"],"speed":["35"],"durability":["56"],"power":["31"],"combat":["28"]},"biography":{"full-name":[""],"alter-egos":["No alter egos found."],"aliases":["-"],"place-of-birth":["-"],"first-appearance":["Amazing Spider-Man #8 (1964)"],"publisher":["Marvel Comics"],"alignment":["bad"]},"appearance":{"gender":["-"],"race":["null"],"height":["6'6","198 cm"],"weight":["800 lb","360 kg"],"eye-color":["Yellow"],"hair-color":["-"]},"work":{"occupation":["Robot"],"base":["-"]},"connections":{"group-affiliation":["-"],"relatives":["-"]},"image":{"url":["https://www.superherodb.com/pictures2/portraits/10/100/1037.jpg"]}}
